sangaboard/__init__.py
sangaboard/extensible_serial_instrument.py
sangaboard/sangaboard.py
sangaboard-0.3.3.dist-info/LICENSE.txt
sangaboard-0.3.3.dist-info/METADATA
sangaboard-0.3.3.dist-info/WHEEL
sangaboard-0.3.3.dist-info/top_level.txt
sangaboard-0.3.3.dist-info/zip-safe
sangaboard-0.3.3.dist-info/RECORD
