Metadata-Version: 2.1
Name: sangaboard
Version: 0.3.3
Summary: Communication to the Sangaboard unipolar motor driver
Home-page: http://www.gitlab.com/bath_open_instrumentation_group/pysangaboard
Author: Bath Open INstrumentation Group
Author-email: r.w.bowman@bath.ac.uk
License: UNKNOWN
Keywords: arduino,serial,motor-driver
Platform: UNKNOWN
Classifier: Development Status :: 5 - Production/Stable
Classifier: License :: OSI Approved :: GNU General Public License v3 (GPLv3)
Classifier: Programming Language :: Python :: 2.7
Classifier: Programming Language :: Python :: 3.7
License-File: LICENSE.txt
Requires-Dist: pyserial
Requires-Dist: future
Requires-Dist: numpy
Requires-Dist: semantic-version
Provides-Extra: dev
Requires-Dist: pytest ; extra == 'dev'
